elasticstack/__init__.py
elasticstack/apps.py
elasticstack/backends.py
elasticstack/fields.py
elasticstack/forms.py
elasticstack/models.py
elasticstack/utils.py
elasticstack/views.py
elasticstack/management/__init__.py
elasticstack/management/commands/__init__.py
elasticstack/management/commands/show_document.py
elasticstack/management/commands/show_mapping.py
elasticstack-0.5.0.dist-info/DESCRIPTION.rst
elasticstack-0.5.0.dist-info/METADATA
elasticstack-0.5.0.dist-info/RECORD
elasticstack-0.5.0.dist-info/WHEEL
elasticstack-0.5.0.dist-info/metadata.json
elasticstack-0.5.0.dist-info/top_level.txt
