Metadata-Version: 2.0
Name: elasticstack
Version: 0.5.0
Summary: Configurable indexing and other extras for Haystack (with ElasticSearch biases).
Home-page: https://github.com/bennylope/elasticstack
Author: Ben Lopatin
Author-email: ben@wellfire.co
License: BSD
Keywords: elasticstack
Platform: UNKNOWN
Classifier: Development Status :: 4 - Beta
Classifier: Framework :: Django
Classifier: Intended Audience :: Developers
Classifier: License :: OSI Approved :: BSD License
Classifier: Natural Language :: English
Classifier: Programming Language :: Python :: 2
Classifier: Programming Language :: Python :: 2.7
Classifier: Programming Language :: Python :: 3
Classifier: Programming Language :: Python :: 3.4
Classifier: Programming Language :: Python :: 3.5
Requires-Dist: Django (>=1.8)
Requires-Dist: django-haystack (>=2.0.0)
